Topsis/__init__.py
Topsis/__main__.py
Nimish_102017084_Topsis-1.0.1.dist-info/LICENSE.md
Nimish_102017084_Topsis-1.0.1.dist-info/METADATA
Nimish_102017084_Topsis-1.0.1.dist-info/WHEEL
Nimish_102017084_Topsis-1.0.1.dist-info/entry_points.txt
Nimish_102017084_Topsis-1.0.1.dist-info/top_level.txt
Nimish_102017084_Topsis-1.0.1.dist-info/RECORD
