Metadata-Version: 2.1
Name: Nimish-102017084-Topsis
Version: 1.0.1
Summary: Calculates TOPSIS on the given dataset!
Home-page: https://github.com/nimish-star/Topsis-Nimish-102017084
Author: Nimish Lakhmani
Author-email: nimishlakhmani@gmail.com
License: MIT
Classifier: License :: OSI Approved :: MIT License
Classifier: Programming Language :: Python :: 3.8
Classifier: Programming Language :: Python :: 3.9
Classifier: Programming Language :: Python :: 3.10
License-File: LICENSE.md
Requires-Dist: pandas
